here_here/__init__.py
here_here/here.py
here_here-1.1.14.dist-info/METADATA
here_here-1.1.14.dist-info/WHEEL
here_here-1.1.14.dist-info/RECORD
