Metadata-Version: 2.4
Name: here-here
Version: 1.1.14
Summary: Python package that replicates the R package called 'here'.
Project-URL: Homepage, https://github.com/michaelboerman/here
Project-URL: Issues, https://github.com/michaelboerman/here/issues
Author-email: Michael Boerman <michaelboerman@hey.com>
Classifier: License :: OSI Approved :: MIT License
Classifier: Operating System :: OS Independent
Classifier: Programming Language :: Python :: 3
Requires-Python: >=3.8
